api_guard/__init__.py
api_guard/apps.py
api_guard/middleware.py
django_api_guard-0.1.0.dist-info/licenses/LICENSE
django_api_guard-0.1.0.dist-info/METADATA
django_api_guard-0.1.0.dist-info/WHEEL
django_api_guard-0.1.0.dist-info/top_level.txt
django_api_guard-0.1.0.dist-info/RECORD
