Metadata-Version: 2.4
Name: django-api-guard
Version: 0.1.0
Summary: A middleware to restrict browser access to Django APIs
Author-email: Mojtaba Zarreh <mojtabazarreh@yahoo.com>
Classifier: Framework :: Django
Classifier: Programming Language :: Python :: 3
Requires-Python: >=3.8
License-File: LICENSE
Requires-Dist: Django>=3.2
Dynamic: license-file
